{
  "url": "https://www.bioforce.org/learn/alumni/",
  "title": "Alumni - Bioforce",
  "content": ":\n\n**formations proposées :**\n- bachelor humanitaire post-bac\n- certifications :\n  - responsable de l’environnement de travail et de la logistique humanitaire\n  - responsable rh et finances\n  - logisticien\n  - responsable logistique\n  - coordinateur de programme\n  - humanitarian programme manager\n  - responsable de projets eau, hygiène et assainissement\n  - responsable de projets protection de l’enfance en situation d’urgence\n- validation des acquis de l'expérience\n- formation courte continue\n\n**modalités d'inscription :**\n- inscription possible pour le bachelor humanitaire via un lien d'inscription.\n\n**événements à venir :**\n- webinaires, salons, réunions d’information en mars 2025.\n\n**ressources pour les anciens élèves :**\n- bionet (groupe linkedin)\n- l’echo des biofs (groupe facebook)\n- accès à biomoodle pour les supports de cours.\n\nc) sections éliminées :\n- tout texte promotionnel, technique ou sans valeur informative a été retiré pour se concentrer sur les informations utiles aux candidats.",
  "category": "formation",
  "timestamp": "2025-03-20T09:36:13.151332",
  "language": "fr",
  "relevance_score": 0.85,
  "pdf_content": "",
  "pdf_path": ""
}