{
  "url": "https://www.bioforce.org/formation/responsable-de-lenvironnement-de-travail-et-de-la-logistique-humanitaire-admission-2e-annee/",
  "title": "Bachelor Responsable de l'Environnement de Travail et de la Logistique Humanitaire | Admission 2e année - Bioforce",
  "content": "Nouveau | Eligible CPF Coordinateur de programme humanitaire | parcours à distance A DISTANCE Formation 8 mois Mission 6 mois 1 session(s) disponible(s) lire plus",
  "category": "formation",
  "timestamp": "2025-03-18T12:33:18.082294",
  "language": "fr",
  "relevance_score": 0.75,
  "pdf_content": "",
  "pdf_path": ""
}